nhl_statsapi/__init__.py
nhl_statsapi-0.1.0.dist-info/WHEEL
nhl_statsapi-0.1.0.dist-info/METADATA
nhl_statsapi-0.1.0.dist-info/RECORD
