Metadata-Version: 2.1
Name: nhl-statsapi
Version: 0.1.0
Summary: NHL Stats API
Home-page: https://github.com/Munsterberg/nhl_statsapi
License: MIT
Keywords: nhl,api,hockey,stats
Author: munsterberg
Author-email: jetrussell93@gmail.com
Requires-Python: >=3.7,<4.0
Classifier: License :: OSI Approved :: MIT License
Classifier: Programming Language :: Python :: 3
Classifier: Programming Language :: Python :: 3.7
Classifier: Programming Language :: Python :: 3.8
Classifier: Programming Language :: Python :: 3.9
Project-URL: Repository, https://github.com/Munsterberg/nhl_statsapi
